reedmuller/reedmuller.py
reedmuller/rmdecode.py
reedmuller/rmencode.py
reedmuller-1.1.0.dist-info/METADATA
reedmuller-1.1.0.dist-info/RECORD
reedmuller-1.1.0.dist-info/WHEEL
reedmuller-1.1.0.dist-info/top_level.txt
